sdnv/__init__.py
sdnv-0.1.0.dist-info/DESCRIPTION.rst
sdnv-0.1.0.dist-info/METADATA
sdnv-0.1.0.dist-info/RECORD
sdnv-0.1.0.dist-info/WHEEL
sdnv-0.1.0.dist-info/metadata.json
sdnv-0.1.0.dist-info/top_level.txt
